{
  "project_info": {
    "project_number": "186192969212",
    "project_id": "ares-855b3",
    "storage_bucket": "ares-855b3.firebasestorage.app"
  },
  "client": [
    {
      "client_info": {
        "mobilesdk_app_id": "1:186192969212:android:1af2fb657d9b1631364679",
        "android_client_info": {
          "package_name": "com.soladev.ares"
        }
      },
      "oauth_client": [],
      "api_key": [
        {
          "current_key": "AIzaSyAdqNw0BeWkvTB0028-Jn7cArnogh6Em4I"
        }
      ],
      "services": {
        "appinvite_service": {
          "other_platform_oauth_client": []
        }
      }
    }
  ],
  "configuration_version": "1"
}